optax/__init__.py
optax/optax_test.py
optax/_src/alias.py
optax/_src/alias_test.py
optax/_src/base.py
optax/_src/base_test.py
optax/_src/clipping.py
optax/_src/clipping_test.py
optax/_src/combine.py
optax/_src/combine_test.py
optax/_src/constrain.py
optax/_src/constrain_test.py
optax/_src/factorized.py
optax/_src/factorized_test.py
optax/_src/float64_test.py
optax/_src/linear_algebra.py
optax/_src/linear_algebra_test.py
optax/_src/lookahead.py
optax/_src/lookahead_test.py
optax/_src/numerics.py
optax/_src/numerics_test.py
optax/_src/schedule.py
optax/_src/transform.py
optax/_src/transform_test.py
optax/_src/update.py
optax/_src/update_test.py
optax/_src/utils.py
optax/_src/utils_test.py
optax/_src/wrappers.py
optax/_src/wrappers_test.py
optax/contrib/__init__.py
optax/contrib/cocob.py
optax/contrib/cocob_test.py
optax/contrib/complex_valued.py
optax/contrib/complex_valued_test.py
optax/contrib/dadapt_adamw.py
optax/contrib/dadapt_adamw_test.py
optax/contrib/mechanic.py
optax/contrib/mechanic_test.py
optax/contrib/privacy.py
optax/contrib/privacy_test.py
optax/contrib/prodigy.py
optax/contrib/prodigy_test.py
optax/contrib/reduce_on_plateau.py
optax/contrib/reduce_on_plateau_test.py
optax/contrib/sam.py
optax/contrib/sam_test.py
optax/losses/__init__.py
optax/losses/_classification.py
optax/losses/_classification_test.py
optax/losses/_ranking.py
optax/losses/_ranking_test.py
optax/losses/_regression.py
optax/losses/_regression_test.py
optax/losses/_smoothing.py
optax/losses/_smoothing_test.py
optax/monte_carlo/__init__.py
optax/monte_carlo/control_variates.py
optax/monte_carlo/control_variates_test.py
optax/monte_carlo/stochastic_gradient_estimators.py
optax/monte_carlo/stochastic_gradient_estimators_test.py
optax/projections/__init__.py
optax/projections/_projections.py
optax/projections/_projections_test.py
optax/schedules/__init__.py
optax/schedules/_inject.py
optax/schedules/_inject_test.py
optax/schedules/_join.py
optax/schedules/_join_test.py
optax-0.1.9.dist-info/LICENSE
optax-0.1.9.dist-info/WHEEL
optax-0.1.9.dist-info/METADATA
optax-0.1.9.dist-info/RECORD
