Metadata-Version: 2.1
Name: optax
Version: 0.1.9
Summary: A gradient processing and optimisation library in JAX.
Keywords: python,machine learning,reinforcement-learning
Author-email: DeepMind <optax-dev@google.com>
Requires-Python: >=3.9
Classifier: Environment :: Console
Classifier: Programming Language :: Python
Classifier: Intended Audience :: Developers
Classifier: Operating System :: OS Independent
Classifier: Programming Language :: Python :: 3
Classifier: Intended Audience :: Science/Research
Classifier: Development Status :: 4 - Beta
Classifier: License :: OSI Approved :: Apache Software License
Classifier: Topic :: Scientific/Engineering :: Artificial Intelligence
Classifier: Topic :: Software Development :: Libraries :: Python Modules
Requires-Dist: absl-py>=0.7.1
Requires-Dist: chex>=0.1.7
Requires-Dist: jax>=0.1.55
Requires-Dist: jaxlib>=0.1.37
Requires-Dist: numpy>=1.18.0
Requires-Dist: sphinx>=6.0.0 ; extra == "docs"
Requires-Dist: sphinx-book-theme>=1.0.1 ; extra == "docs"
Requires-Dist: sphinxcontrib-katex ; extra == "docs"
Requires-Dist: sphinx-autodoc-typehints ; extra == "docs"
Requires-Dist: ipython>=8.8.0 ; extra == "docs"
Requires-Dist: myst-nb>=1.0.0 ; extra == "docs"
Requires-Dist: matplotlib>=3.5.0 ; extra == "docs"
Requires-Dist: dm-haiku>=0.0.11 ; extra == "docs"
Requires-Dist: sphinx-gallery>=0.14.0 ; extra == "docs"
Requires-Dist: sphinx-collections>=0.0.1 ; extra == "docs"
Requires-Dist: tensorflow>=2.4.0 ; extra == "docs"
Requires-Dist: tensorflow-datasets>=4.2.0 ; extra == "docs"
Requires-Dist: absl-py>=1.0.0 ; extra == "dp-accounting"
Requires-Dist: attrs>=21.4.0 ; extra == "dp-accounting"
Requires-Dist: mpmath>=1.2.1 ; extra == "dp-accounting"
Requires-Dist: numpy>=1.21.4 ; extra == "dp-accounting"
Requires-Dist: scipy>=1.7.1 ; extra == "dp-accounting"
Requires-Dist: dm-haiku>=0.0.3 ; extra == "examples"
Requires-Dist: tensorflow-datasets>=4.2.0 ; extra == "examples"
Requires-Dist: tensorflow>=2.4.0 ; extra == "examples"
Requires-Dist: dm-haiku>=0.0.3 ; extra == "test"
Requires-Dist: dm-tree>=0.1.7 ; extra == "test"
Requires-Dist: flax==0.5.3 ; extra == "test"
Project-URL: documentation, https://optax.readthedocs.io/
Project-URL: homepage, https://github.com/deepmind/optax
Project-URL: repository, https://github.com/deepmind/optax
Provides-Extra: docs
Provides-Extra: dp-accounting
Provides-Extra: examples
Provides-Extra: test
